zmk_layout/__init__.py
zmk_layout/__version__.py
zmk_layout/py.typed
zmk_layout/builders/__init__.py
zmk_layout/builders/behavior.py
zmk_layout/builders/binding.py
zmk_layout/builders/combo.py
zmk_layout/builders/generator.py
zmk_layout/builders/macro.py
zmk_layout/core/__init__.py
zmk_layout/core/exceptions.py
zmk_layout/core/layout.py
zmk_layout/core/optional_deps.py
zmk_layout/core/managers/__init__.py
zmk_layout/core/managers/behavior_manager.py
zmk_layout/core/managers/layer_manager.py
zmk_layout/core/managers/layer_proxy.py
zmk_layout/generators/__init__.py
zmk_layout/generators/config_generator.py
zmk_layout/generators/core_operations.py
zmk_layout/generators/template_context.py
zmk_layout/generators/zmk_generator.py
zmk_layout/infrastructure/__init__.py
zmk_layout/infrastructure/debug_tools.py
zmk_layout/infrastructure/performance.py
zmk_layout/infrastructure/provider_builder.py
zmk_layout/infrastructure/template_context.py
zmk_layout/models/__init__.py
zmk_layout/models/base.py
zmk_layout/models/behaviors.py
zmk_layout/models/core.py
zmk_layout/models/keymap.py
zmk_layout/models/metadata.py
zmk_layout/models/types.py
zmk_layout/parsers/__init__.py
zmk_layout/parsers/ast_behavior_converter.py
zmk_layout/parsers/ast_nodes.py
zmk_layout/parsers/ast_walker.py
zmk_layout/parsers/devicetree.lark
zmk_layout/parsers/dt_parser.py
zmk_layout/parsers/keymap_parser.py
zmk_layout/parsers/keymap_processors.py
zmk_layout/parsers/lark_dt_parser.py
zmk_layout/parsers/parsing_models.py
zmk_layout/parsers/section_extractor.py
zmk_layout/parsers/tokenizer.py
zmk_layout/parsers/zmk_keymap_parser.py
zmk_layout/processing/__init__.py
zmk_layout/processing/chain_composition.py
zmk_layout/processing/processor_pipeline.py
zmk_layout/processing/transformation_pipeline.py
zmk_layout/providers/__init__.py
zmk_layout/providers/configuration.py
zmk_layout/providers/factory.py
zmk_layout/providers/file.py
zmk_layout/providers/logger.py
zmk_layout/providers/template.py
zmk_layout-0.0.2.dist-info/METADATA
zmk_layout-0.0.2.dist-info/WHEEL
zmk_layout-0.0.2.dist-info/RECORD
