Metadata-Version: 2.4
Name: zmk-layout
Version: 0.0.2
Summary: ZMK keyboard layout manipulation library with fluent API
Project-URL: Homepage, https://github.com/CaddyGlow/zmk-layout
Project-URL: Repository, https://github.com/CaddyGlow/zmk-layout
Author-email: ZMK Layout Library Contributors <developers@example.com>
License: MIT
Requires-Python: >=3.11
Requires-Dist: lark>=1.2.2
Requires-Dist: pydantic>=2.11.0
Requires-Dist: typing-extensions>=4.0.0
Provides-Extra: dev
Requires-Dist: mypy>=1.15; extra == 'dev'
Requires-Dist: pytest-cov>=4.0; extra == 'dev'
Requires-Dist: pytest>=8.0; extra == 'dev'
Requires-Dist: ruff>=0.11; extra == 'dev'
Provides-Extra: display
Requires-Dist: rich>=13.0; extra == 'display'
Provides-Extra: full
Requires-Dist: jinja2>=3.0; extra == 'full'
Requires-Dist: jsonpatch>=1.32; extra == 'full'
Requires-Dist: lark>=1.1; extra == 'full'
Requires-Dist: rich>=13.0; extra == 'full'
Provides-Extra: parsing
Requires-Dist: lark>=1.1; extra == 'parsing'
Provides-Extra: templating
Requires-Dist: jinja2>=3.0; extra == 'templating'
